{
    "backend": "flask",
    "db_name": "",
    "db_pass": "",
    "db_type": "sqlite",
    "db_user": "",
    "dbms": "1",
    "description": "generated product",
    "design": "soft-ui-dashboard",
    "docker": "1",
    "err_code": 0,
    "frontend": "",
    "heroku": "0",
    "pattern": "mvc",
    "pro": "0",
    "task_id": "cf16fe42-650c-4f92-bcf2-22edc7e06051",
    "task_info": "Upload Sources [0%] - 334 files",
    "task_output": "cf16fe42-650c-4f92-bcf2-22edc7e06051.zip",
    "task_result": "SUCCESS",
    "task_state": "RUNNING",
    "task_ts_end": "2023-08-24-14-29-50",
    "task_ts_start": "2023-08-24-14-29-47"
}